zophar/__init__.py
zophar/__main__.py
zophar/browser.py
zophar/parsers/__init__.py
zophar/parsers/gamelistpage.py
zophar/parsers/gamepage.py
zophar/parsers/infopage.py
zophar/parsers/parser.py
zophar/parsers/searchpage.py
zophar/parsers/types.py
zophar-1.0.1.dist-info/METADATA
zophar-1.0.1.dist-info/WHEEL
zophar-1.0.1.dist-info/licenses/LICENSE
zophar-1.0.1.dist-info/RECORD
