Metadata-Version: 2.4
Name: zophar
Version: 1.0.1
Summary: Asynchronous Python music browser of the Zophar domain.
Project-URL: Documentation, https://github.com/dudanov/python-zophar
Project-URL: Home Page, https://github.com/dudanov/python-zophar
Project-URL: Issue Tracker, https://github.com/dudanov/python-zophar/issues
Project-URL: Source Code, https://github.com/dudanov/python-zophar.git
Author-email: Sergey Dudanov <sergey.dudanov@gmail.com>
Maintainer-email: Sergey Dudanov <sergey.dudanov@gmail.com>
License-Expression: Apache-2.0
License-File: LICENSE
Keywords: async,browser,console,music,zophar
Classifier: Development Status :: 4 - Beta
Classifier: Framework :: AsyncIO
Classifier: Intended Audience :: Developers
Classifier: Natural Language :: Russian
Classifier: Operating System :: OS Independent
Classifier: Programming Language :: Python
Classifier: Programming Language :: Python :: 3 :: Only
Classifier: Programming Language :: Python :: 3.12
Classifier: Programming Language :: Python :: 3.13
Classifier: Topic :: Software Development :: Libraries :: Python Modules
Requires-Python: <3.14,>=3.12
Requires-Dist: aiohttp>=3.10
Requires-Dist: beautifulsoup4>=4.13
Requires-Dist: lxml>=5.3
